<annotation>
	<folder>images</folder>
	<filename>screenshot2.png</filename>
	<path>C:\Users\User\Documents\Python_Scripts\wfmapi\rivenchecker\RivenOCR\New folder\images\screenshot2.png</path>
	<source>
		<database>Unknown</database>
	</source>
	<size>
		<width>1240</width>
		<height>733</height>
		<depth>3</depth>
	</size>
	<segmented>0</segmented>
	<object>
		<name>link</name>
		<pose>Unspecified</pose>
		<truncated>0</truncated>
		<difficult>0</difficult>
		<bndbox>
			<xmin>391</xmin>
			<ymin>662</ymin>
			<xmax>611</xmax>
			<ymax>693</ymax>
		</bndbox>
	</object>
	<object>
		<name>link</name>
		<pose>Unspecified</pose>
		<truncated>0</truncated>
		<difficult>0</difficult>
		<bndbox>
			<xmin>273</xmin>
			<ymin>631</ymin>
			<xmax>500</xmax>
			<ymax>663</ymax>
		</bndbox>
	</object>
	<object>
		<name>link</name>
		<pose>Unspecified</pose>
		<truncated>0</truncated>
		<difficult>0</difficult>
		<bndbox>
			<xmin>391</xmin>
			<ymin>600</ymin>
			<xmax>607</xmax>
			<ymax>632</ymax>
		</bndbox>
	</object>
	<object>
		<name>link</name>
		<pose>Unspecified</pose>
		<truncated>0</truncated>
		<difficult>0</difficult>
		<bndbox>
			<xmin>248</xmin>
			<ymin>571</ymin>
			<xmax>463</xmax>
			<ymax>603</ymax>
		</bndbox>
	</object>
	<object>
		<name>link</name>
		<pose>Unspecified</pose>
		<truncated>0</truncated>
		<difficult>0</difficult>
		<bndbox>
			<xmin>272</xmin>
			<ymin>541</ymin>
			<xmax>499</xmax>
			<ymax>571</ymax>
		</bndbox>
	</object>
	<object>
		<name>link</name>
		<pose>Unspecified</pose>
		<truncated>0</truncated>
		<difficult>0</difficult>
		<bndbox>
			<xmin>389</xmin>
			<ymin>511</ymin>
			<xmax>608</xmax>
			<ymax>541</ymax>
		</bndbox>
	</object>
	<object>
		<name>link</name>
		<pose>Unspecified</pose>
		<truncated>0</truncated>
		<difficult>0</difficult>
		<bndbox>
			<xmin>272</xmin>
			<ymin>481</ymin>
			<xmax>498</xmax>
			<ymax>513</ymax>
		</bndbox>
	</object>
	<object>
		<name>link</name>
		<pose>Unspecified</pose>
		<truncated>0</truncated>
		<difficult>0</difficult>
		<bndbox>
			<xmin>273</xmin>
			<ymin>450</ymin>
			<xmax>500</xmax>
			<ymax>480</ymax>
		</bndbox>
	</object>
	<object>
		<name>link</name>
		<pose>Unspecified</pose>
		<truncated>0</truncated>
		<difficult>0</difficult>
		<bndbox>
			<xmin>272</xmin>
			<ymin>419</ymin>
			<xmax>498</xmax>
			<ymax>450</ymax>
		</bndbox>
	</object>
	<object>
		<name>link</name>
		<pose>Unspecified</pose>
		<truncated>0</truncated>
		<difficult>0</difficult>
		<bndbox>
			<xmin>389</xmin>
			<ymin>387</ymin>
			<xmax>609</xmax>
			<ymax>423</ymax>
		</bndbox>
	</object>
	<object>
		<name>link</name>
		<pose>Unspecified</pose>
		<truncated>0</truncated>
		<difficult>0</difficult>
		<bndbox>
			<xmin>432</xmin>
			<ymin>360</ymin>
			<xmax>749</xmax>
			<ymax>386</ymax>
		</bndbox>
	</object>
	<object>
		<name>link</name>
		<pose>Unspecified</pose>
		<truncated>0</truncated>
		<difficult>0</difficult>
		<bndbox>
			<xmin>316</xmin>
			<ymin>329</ymin>
			<xmax>534</xmax>
			<ymax>358</ymax>
		</bndbox>
	</object>
	<object>
		<name>link</name>
		<pose>Unspecified</pose>
		<truncated>0</truncated>
		<difficult>0</difficult>
		<bndbox>
			<xmin>207</xmin>
			<ymin>299</ymin>
			<xmax>439</xmax>
			<ymax>331</ymax>
		</bndbox>
	</object>
	<object>
		<name>link</name>
		<pose>Unspecified</pose>
		<truncated>0</truncated>
		<difficult>0</difficult>
		<bndbox>
			<xmin>482</xmin>
			<ymin>300</ymin>
			<xmax>712</xmax>
			<ymax>330</ymax>
		</bndbox>
	</object>
	<object>
		<name>link</name>
		<pose>Unspecified</pose>
		<truncated>0</truncated>
		<difficult>0</difficult>
		<bndbox>
			<xmin>753</xmin>
			<ymin>299</ymin>
			<xmax>927</xmax>
			<ymax>328</ymax>
		</bndbox>
	</object>
	<object>
		<name>link</name>
		<pose>Unspecified</pose>
		<truncated>0</truncated>
		<difficult>0</difficult>
		<bndbox>
			<xmin>3</xmin>
			<ymin>296</ymin>
			<xmax>166</xmax>
			<ymax>327</ymax>
		</bndbox>
	</object>
	<object>
		<name>link</name>
		<pose>Unspecified</pose>
		<truncated>0</truncated>
		<difficult>0</difficult>
		<bndbox>
			<xmin>431</xmin>
			<ymin>267</ymin>
			<xmax>642</xmax>
			<ymax>298</ymax>
		</bndbox>
	</object>
	<object>
		<name>link</name>
		<pose>Unspecified</pose>
		<truncated>0</truncated>
		<difficult>0</difficult>
		<bndbox>
			<xmin>482</xmin>
			<ymin>238</ymin>
			<xmax>712</xmax>
			<ymax>267</ymax>
		</bndbox>
	</object>
	<object>
		<name>link</name>
		<pose>Unspecified</pose>
		<truncated>0</truncated>
		<difficult>0</difficult>
		<bndbox>
			<xmin>207</xmin>
			<ymin>239</ymin>
			<xmax>441</xmax>
			<ymax>269</ymax>
		</bndbox>
	</object>
	<object>
		<name>link</name>
		<pose>Unspecified</pose>
		<truncated>0</truncated>
		<difficult>0</difficult>
		<bndbox>
			<xmin>3</xmin>
			<ymin>235</ymin>
			<xmax>165</xmax>
			<ymax>270</ymax>
		</bndbox>
	</object>
	<object>
		<name>link</name>
		<pose>Unspecified</pose>
		<truncated>0</truncated>
		<difficult>0</difficult>
		<bndbox>
			<xmin>432</xmin>
			<ymin>209</ymin>
			<xmax>643</xmax>
			<ymax>238</ymax>
		</bndbox>
	</object>
	<object>
		<name>link</name>
		<pose>Unspecified</pose>
		<truncated>0</truncated>
		<difficult>0</difficult>
		<bndbox>
			<xmin>4</xmin>
			<ymin>147</ymin>
			<xmax>166</xmax>
			<ymax>175</ymax>
		</bndbox>
	</object>
	<object>
		<name>link</name>
		<pose>Unspecified</pose>
		<truncated>0</truncated>
		<difficult>0</difficult>
		<bndbox>
			<xmin>207</xmin>
			<ymin>147</ymin>
			<xmax>441</xmax>
			<ymax>178</ymax>
		</bndbox>
	</object>
	<object>
		<name>link</name>
		<pose>Unspecified</pose>
		<truncated>0</truncated>
		<difficult>0</difficult>
		<bndbox>
			<xmin>483</xmin>
			<ymin>147</ymin>
			<xmax>711</xmax>
			<ymax>178</ymax>
		</bndbox>
	</object>
	<object>
		<name>link</name>
		<pose>Unspecified</pose>
		<truncated>0</truncated>
		<difficult>0</difficult>
		<bndbox>
			<xmin>753</xmin>
			<ymin>146</ymin>
			<xmax>923</xmax>
			<ymax>180</ymax>
		</bndbox>
	</object>
	<object>
		<name>link</name>
		<pose>Unspecified</pose>
		<truncated>0</truncated>
		<difficult>0</difficult>
		<bndbox>
			<xmin>390</xmin>
			<ymin>176</ymin>
			<xmax>610</xmax>
			<ymax>208</ymax>
		</bndbox>
	</object>
	<object>
		<name>link</name>
		<pose>Unspecified</pose>
		<truncated>0</truncated>
		<difficult>0</difficult>
		<bndbox>
			<xmin>752</xmin>
			<ymin>236</ymin>
			<xmax>926</xmax>
			<ymax>269</ymax>
		</bndbox>
	</object>
</annotation>
